A2L.py
ASSAM.py
README.md
TrackA2L.py
hexa2l.py
setup.py
assamer.egg-info/PKG-INFO
assamer.egg-info/SOURCES.txt
assamer.egg-info/dependency_links.txt
assamer.egg-info/requires.txt
assamer.egg-info/top_level.txt