Metadata-Version: 2.1
Name: assamer
Version: 1.3.7
Summary: ASAP2 (A2L) and ASSAM Library
Home-page: UNKNOWN
Author: Veysel KANTARCILAR
Author-email: kantrveysel@gmail.com
License: UNKNOWN
Platform: UNKNOWN
